_tomotopy.cpython-39-darwin.so
_tomotopy_avx.cpython-39-darwin.so
_tomotopy_avx2.cpython-39-darwin.so
_tomotopy_sse2.cpython-39-darwin.so
tomotopy/__init__.py
tomotopy/_call_utils.py
tomotopy/_show_progress.py
tomotopy/_summary.py
tomotopy/_version.py
tomotopy/auto_labeling_code.rst
tomotopy/auto_labeling_code_with_porter.rst
tomotopy/coherence.py
tomotopy/documentation.kr.rst
tomotopy/documentation.rst
tomotopy/label.py
tomotopy/utils.py
tomotopy/viewer/__init__.py
tomotopy/viewer/__main__.py
tomotopy/viewer/template.html
tomotopy/viewer/viewer_server.py
tomotopy-0.13.0.dist-info/LICENSE
tomotopy-0.13.0.dist-info/METADATA
tomotopy-0.13.0.dist-info/WHEEL
tomotopy-0.13.0.dist-info/top_level.txt
tomotopy-0.13.0.dist-info/RECORD
