Metadata-Version: 2.1
Name: tomotopy
Version: 0.13.0
Summary: Tomoto, Topic Modeling Tool for Python
Home-page: https://github.com/bab2min/tomotopy
Author: bab2min
Author-email: bab2min@gmail.com
License: MIT License
Keywords: NLP,Topic Model
Classifier: Development Status :: 3 - Alpha
Classifier: Intended Audience :: Information Technology
Classifier: Intended Audience :: Science/Research
Classifier: Topic :: Software Development :: Libraries
Classifier: Topic :: Text Processing :: Linguistic
Classifier: Topic :: Scientific/Engineering :: Information Analysis
Classifier: License :: OSI Approved :: MIT License
Classifier: Programming Language :: Python :: 3
Classifier: Programming Language :: C++
Classifier: Operating System :: Microsoft :: Windows :: Windows Vista
Classifier: Operating System :: Microsoft :: Windows :: Windows 7
Classifier: Operating System :: Microsoft :: Windows :: Windows 8
Classifier: Operating System :: Microsoft :: Windows :: Windows 8.1
Classifier: Operating System :: Microsoft :: Windows :: Windows 10
Classifier: Operating System :: POSIX
Classifier: Operating System :: MacOS
License-File: LICENSE
Requires-Dist: numpy<2,>=1.11.0
